{"subs":{"Bomb_Splash":{"Id":0,"InkSaverType":"C","Name":"Bomb_Splash","param":{"mBringCloseRateCrossVec":0.7,"mBringCloseRateMoveVec":0.7,"mBurst_Damage_Far":300,"mBurst_Damage_Far_Coop":300,"mBurst_Damage_Far_Enemy":300,"mBurst_Damage_Far_LastBoss":300,"mBurst_Damage_Far_Mission":300,"mBurst_Damage_Far_Rival":300,"mBurst_Damage_Far_Tutorial":300,"mBurst_Damage_Near":1800,"mBurst_Damage_Near_Coop":1800,"mBurst_Damage_Near_Enemy":1800,"mBurst_Damage_Near_LastBoss":1800,"mBurst_Damage_Near_Mission":1800,"mBurst_Damage_Near_Rival":1800,"mBurst_Damage_Near_Tutorial":1800,"mBurst_KnockBackCoreImpact":3,"mBurst_KnockBackCoreImpact_LastBoss":3,"mBurst_KnockBackKb":0.8,"mBurst_KnockBackRadius":120,"mBurst_KnockBackRadius_LastBoss":120,"mBurst_PaintR":40,"mBurst_PaintR_LastBoss":55,"mBurst_Radius_Far":70,"mBurst_Radius_Far_Coop":80,"mBurst_Radius_Far_Enemy":80,"mBurst_Radius_Far_LastBoss":95,"mBurst_Radius_Far_Mission":80,"mBurst_Radius_Far_Rival":80,"mBurst_Radius_Far_Tutorial":80,"mBurst_Radius_Near":40,"mBurst_Radius_Near_Coop":40,"mBurst_Radius_Near_Enemy":30,"mBurst_Radius_Near_LastBoss":55,"mBurst_Radius_Near_Mission":40,"mBurst_Radius_Near_Rival":40,"mBurst_Radius_Near_Tutorial":65,"mBurst_SeFrm":10,"mBurst_SplashAroundFuzzyRate":2,"mBurst_SplashNum":15,"mBurst_SplashNum_LastBoss":15,"mBurst_SplashOfstY":5,"mBurst_SplashOfstY_LastBoss":5,"mBurst_SplashPaintR":10,"mBurst_SplashPaintR_LastBoss":10,"mBurst_SplashPitH":45,"mBurst_SplashPitH_LastBoss":45,"mBurst_SplashPitL":5,"mBurst_SplashPitL_LastBoss":5,"mBurst_SplashVelH":5.4,"mBurst_SplashVelH_LastBoss":5.4,"mBurst_SplashVelL":4.8,"mBurst_SplashVelL_LastBoss":4.8,"mBurst_WaitFrm":30,"mBurst_WarnFrm":30,"mCollisionSeSilentFrame":4,"mCollisionSeVelDotGndNrm":0.08,"mCollisionSeVelDotGndTimes":1.2,"mContactDashPanelAddSpeed":9.5,"mContactDashPanelAddSpeedVS_SettingOcta_":9.5,"mContactDashPanelCrossSaveSpeedRate":0.9,"mContactDashPanelCrossSaveSpeedRateVS_SettingOcta_":0.9,"mContactJumpPanelAddSpeed":5,"mContactJumpPanelAddSpeedOneBoundRate":0.7,"mContactJumpPanelAddSpeedOneBoundRateVS_":1,"mContactJumpPanelAddSpeedOneBoundRateVS_SettingOcta_":1,"mContactJumpPanelAddSpeedVS_":2,"mContactJumpPanelAddSpeedVS_SettingOcta_":0,"mContactJumpPanelCrossSaveSpeedRate":1,"mContactJumpPanelCrossSaveSpeedRateVS_":1,"mContactJumpPanelCrossSaveSpeedRateVS_SettingOcta_":1,"mContactJumpPanelMaxNum":2,"mContactJumpPanelMaxNumVS_":2,"mContactJumpPanelMaxNumVS_SettingOcta_":1,"mContactJumpPanelNrmSaveSpeedRateVS_":1,"mContactJumpPanelNrmSaveSpeedRateVS_SettingOcta_":1,"mContactJumpPanelSpeedLimitVS_":5,"mContactJumpPanelVelKdVS_":1,"mCrossPaintRadius":20,"mCrossPaintRadius_LastBoss":20,"mCrossPaintRayLength":20,"mCrossPaintRayLength_LastBoss":20,"mCrossPaintRayRadius":1,"mEffectShakeRange":100,"mFly_AirFrm":4,"mFly_CeilingKf_Y":1,"mFly_CeilingKr_Y":0.5,"mFly_Gravity":0.16,"mFly_InitPit":0.4,"mFly_InitRol":0.12,"mFly_RotI":20,"mFly_RotKd":0.98015,"mFly_VelKd":0.94134,"mFly_WallKf_XZ":0.7,"mFly_WallKf_Y":0.2,"mFly_WallKr":0.2,"mForceSleepFrame":900,"mInkConsume":0.7,"mInkConsume_Coop":0.75,"mInkConsume_Enemy":0,"mInkConsume_LastBoss":0,"mInkConsume_Mission":0.7,"mInkConsume_Rival":0.7,"mInkConsume_Tutorial":0.7,"mLand_AbsorveRt":0.1,"mLand_GndKf":0.2,"mLand_GndKr":0.05,"mLand_GravGndK":0.5,"mLand_GravH":0.08,"mLand_GravKf":0.1,"mLand_GravL":0.016,"mLand_NrmGndKf":0.1,"mLand_RotI":10,"mLand_RotKd":0.96059,"mLand_VelKdXZ":0.92237,"mLand_VelKdY":0.92237,"mShape_SphereD":5,"mShape_SphereR":2,"mShape_SphereRate_LastBoss":1.975}},"Bomb_Suction":{"Id":1,"InkSaverType":"C","Name":"Bomb_Suction","param":{"mBringCloseRateCrossVec":0.7,"mBringCloseRateMoveVec":0.7,"mBurst_Damage_Far":300,"mBurst_Damage_Far_Enemy":300,"mBurst_Damage_Far_LastBoss":300,"mBurst_Damage_Middle":300,"mBurst_Damage_Middle_Enemy":300,"mBurst_Damage_Middle_LastBoss":300,"mBurst_Damage_Near":2200,"mBurst_Damage_Near_Enemy":1800,"mBurst_Damage_Near_LastBoss":1800,"mBurst_KnockBackCoreImpact":3,"mBurst_KnockBackCoreImpact_LastBoss":3,"mBurst_KnockBackKb":0.8,"mBurst_KnockBackRadius":120,"mBurst_KnockBackRadius_LastBoss":120,"mBurst_PaintR":50,"mBurst_PaintR_LastBoss":55,"mBurst_Radius_Far":80,"mBurst_Radius_Far_Enemy":90,"mBurst_Radius_Far_LastBoss":95,"mBurst_Radius_Middle":80,"mBurst_Radius_Middle_Enemy":90,"mBurst_Radius_Middle_LastBoss":95,"mBurst_Radius_Near":50,"mBurst_Radius_Near_Enemy":50,"mBurst_Radius_Near_LastBoss":55,"mBurst_SeFrm":10,"mBurst_SplashAroundFuzzyRate":2,"mBurst_SplashNum":15,"mBurst_SplashNum_LastBoss":15,"mBurst_SplashOfstY":5,"mBurst_SplashOfstY_LastBoss":5,"mBurst_SplashPaintR":10,"mBurst_SplashPaintR_LastBoss":10,"mBurst_SplashPitH":45,"mBurst_SplashPitH_LastBoss":45,"mBurst_SplashPitL":5,"mBurst_SplashPitL_LastBoss":5,"mBurst_SplashVelH":6.4,"mBurst_SplashVelH_LastBoss":6.4,"mBurst_SplashVelL":4.8,"mBurst_SplashVelL_LastBoss":4.8,"mBurst_WaitFrm":90,"mBurst_WarnFrm":30,"mCollisionSeVelDotGndNrm":0.08,"mContactDashPanelAddSpeed_SettingOcta_":9.5,"mContactDashPanelCrossSaveSpeedRate_SettingOcta_":0.9,"mConveyer_Radius":5,"mCrossPaintRadius":25,"mCrossPaintRadius_LastBoss":25,"mCrossPaintRayLength":25,"mCrossPaintRayLength_LastBoss":25,"mCrossPaintRayRadius":1,"mEffectShakeRange":100,"mFly_AirFrm":4,"mFly_Gravity":0.16,"mFly_InitPit":0.4,"mFly_InitRol":0.12,"mFly_RotI":20,"mFly_RotKd":0.98015,"mFly_VelKd":0.94134,"mInkConsume":0.7,"mInkConsume_Enemy":0.7,"mInkConsume_LastBoss":0.7,"mShape_SphereD":5,"mShape_SphereR":2,"mShape_SphereRate_LastBoss":1.975,"mWallCheckOffsetY":4.5}},"Bomb_Quick":{"Id":2,"InkSaverType":"A","Name":"Bomb_Quick","param":{"mBombDamage":250,"mBringCloseRateCrossVec":0.7,"mBringCloseRateMoveVec":0.7,"mBurst_Damage_Far":250,"mBurst_Damage_Middle":350,"mBurst_Damage_Near":350,"mBurst_KnockBackCoreImpact":2,"mBurst_KnockBackKb":0.8,"mBurst_KnockBackRadius":80,"mBurst_PaintR":40,"mBurst_Radius_Far":40,"mBurst_Radius_Middle":32,"mBurst_Radius_Near":32,"mBurst_SplashAroundFuzzyRate":2,"mBurst_SplashNum":10,"mBurst_SplashOfstY":3,"mBurst_SplashPaintR":7,"mBurst_SplashPitH":30,"mBurst_SplashPitL":5,"mBurst_SplashVelH":3.5,"mBurst_SplashVelL":5.2,"mCrossPaintRadius":14,"mCrossPaintRayLength":14,"mCrossPaintRayRadius":1,"mEffectShakeRange":70,"mFly_Gravity":0.16,"mFly_InitPit":0.4,"mFly_InitRol":0.12,"mFly_RotI":20,"mFly_RotKd":0.98015,"mFly_VelKd":0.94134,"mInkConsume":0.4,"mShape_SphereD":5,"mShape_SphereR":2}},"Bomb_Curling":{"Id":3,"InkSaverType":"C","Name":"Bomb_Curling","param":{"mBaseSpeedComeOverRate":0.92,"mBaseSpeedComeOverRateLowSpeed":0.9,"mBaseSpeedComeUnderRate":0.96,"mBaseSpeedComeUnderRateLowSpeed":0.9,"mBaseSpeedMaxCharge":1,"mBaseSpeedMaxCharge_Special":2.6,"mBaseSpeedMinCharge":2.2,"mBaseSpeedMinCharge_Special":1.6,"mBringCloseRateCrossVec":0.7,"mBringCloseRateMoveVec":0.7,"mBurstTimingLowSpeed":0,"mBurstTimingLowSpeedBias":0.4,"mBurstTimingLowSpeedFrame":90,"mBurst_Damage_Far":300,"mBurst_Damage_Far_Enemy":300,"mBurst_Damage_Far_Mission":300,"mBurst_Damage_Near":1800,"mBurst_Damage_Near_Enemy":1500,"mBurst_Damage_Near_Mission":1500,"mBurst_EachLength_Bias":0.65,"mBurst_KnockBackCoreImpact":3,"mBurst_KnockBackKb":0.8,"mBurst_KnockBackRadius":90,"mBurst_PaintR":20,"mBurst_PaintR_Enemy":40,"mBurst_PaintR_MaxCharge":50,"mBurst_PaintR_Mission":40,"mBurst_Radius_Far":50,"mBurst_Radius_Far_Enemy":80,"mBurst_Radius_Far_MaxCharge":80,"mBurst_Radius_Far_Mission":80,"mBurst_Radius_Near":20,"mBurst_Radius_Near_Enemy":40,"mBurst_Radius_Near_MaxCharge":50,"mBurst_Radius_Near_Mission":40,"mBurst_SplashAroundFuzzyRate":2,"mBurst_SplashNum":12,"mBurst_SplashOfstY":5,"mBurst_SplashPaintR":7,"mBurst_SplashPaintR_Enemy":7,"mBurst_SplashPaintR_Mission":7,"mBurst_SplashPitH":33,"mBurst_SplashPitH_Enemy":33,"mBurst_SplashPitH_MaxCharge":-90,"mBurst_SplashPitH_Mission":33,"mBurst_SplashPitL":19,"mBurst_SplashPitL_Enemy":19,"mBurst_SplashPitL_MaxCharge":-90,"mBurst_SplashPitL_Mission":19,"mBurst_SplashVelH":3,"mBurst_SplashVelH_Enemy":4.2,"mBurst_SplashVelH_MaxCharge":4.8,"mBurst_SplashVelH_Mission":4.2,"mBurst_SplashVelL":2.5,"mBurst_SplashVelL_Enemy":3.5,"mBurst_SplashVelL_MaxCharge":4,"mBurst_SplashVelL_Mission":3.5,"mBurst_WaitFrm":120,"mBurst_WarnFrm":90,"mChargeMaxFrame":60,"mChargeTimeCountRate":2,"mColPlayerAddHeight":-5,"mColPlayerOffset":0,"mColPlayerRadius":6,"mCollisionSeSilentFrame":4,"mContactDashPanelAddSpeed":13,"mContactDashPanelAddSpeedVS_SettingOcta_":13,"mContactDashPanelCrossSaveSpeedRate":1,"mContactDashPanelCrossSaveSpeedRateVS_SettingOcta_":1,"mContactJumpPanelAddSpeed":3.1,"mContactJumpPanelAddSpeedOneBoundRate":0.5,"mContactJumpPanelAddSpeedOneBoundRateVS_":1,"mContactJumpPanelAddSpeedOneBoundRateVS_SettingOcta_":1,"mContactJumpPanelAddSpeedVS_":1,"mContactJumpPanelAddSpeedVS_SettingOcta_":0,"mContactJumpPanelCrossSaveSpeedRate":1,"mContactJumpPanelCrossSaveSpeedRateVS_":1,"mContactJumpPanelCrossSaveSpeedRateVS_SettingOcta_":1,"mContactJumpPanelMaxNum":3,"mContactJumpPanelMaxNumVS_":8,"mContactJumpPanelMaxNumVS_SettingOcta_":2,"mContactJumpPanelNrmSaveSpeedRateVS_":1,"mContactJumpPanelNrmSaveSpeedRateVS_SettingOcta_":1,"mContactJumpPanelSpeedLimitVS_":5,"mContactJumpPanelVelKdVS_":1,"mCrossPaintRadius":10,"mCrossPaintRadius_MaxCharge":21,"mCrossPaintRayLength":10,"mCrossPaintRayLength_MaxCharge":21,"mCrossPaintRayRadius":1,"mDamage":200,"mEffectShakeRange":100,"mFly_AirFrm":4,"mFly_Gravity":0.16,"mFly_GravityDraw":0.005,"mFly_RotI":20,"mFly_RotKd":0.98015,"mFly_VelKd":0.94134,"mGuideSpeedMaxCharge":0.06,"mGuideSpeedMaxCharge_Special":0.32,"mGuideSpeedMinCharge":0.25,"mGuideSpeedMinCharge_Special":0.1,"mInitVelAndBaseSpeedHigh":1.3,"mInitVelAndBaseSpeedMid":1.15,"mInitVelMaxCharge":[0,1.2,2],"mInitVelMaxCharge_Special":[0,1.2,5],"mInitVelMinCharge":[0,1.2,4],"mInitVelMinCharge_Special":[0,1.2,2.6],"mInkConsume":0.7,"mInkConsume_Enemy":0.7,"mInkConsume_Mission":0.7,"mJustAirForceGroundAddHeight":3,"mKnockBackCoreImpact":1.5,"mKnockBackDegree":60,"mKnockBackKb":0,"mKnockBackRadius":300,"mLand_AbsorveRt":0.1,"mLand_GndKf":0.2,"mLand_GndKr":0.05,"mLand_GravGndK":0.5,"mLand_GravH":0.01,"mLand_GravKf":0.1,"mLand_GravL":0.01,"mLand_NrmGndKf":0.1,"mLand_RotI":10,"mLand_RotKd":0.96059,"mLand_VelKdXZ":1,"mLand_VelKdY":1,"mLauncherChargeFrame":30,"mLauncherChargeRateForBurstAndPaint":25,"mMinSpeedAir":0.5,"mModelDirection":true,"mModelUpRotateAxisCrossVelDegree":3,"mModelUpRotateAxisVelDegree":1.25,"mModelUpRotateBoundDegree45ToAddDegree":1,"mModelUpRotateBoundDegreeReduce":0.005,"mPaintCheckHeight":20,"mPaintRadius":10,"mPaintRadius_Bias":0.25,"mPaintRadius_MaxCharge":12,"mPaintSpanFrame":2,"mShape_SphereD":5,"mShape_SphereR":2,"mWallCheckOffsetY":4.5}},"Bomb_Robo":{"Id":4,"InkSaverType":"B","Name":"Bomb_Robo","param":{"mBringCloseRateCrossVec":0.7,"mBringCloseRateMoveVec":0.7,"mBurst_Damage_Far":300,"mBurst_Damage_Far_Mission":300,"mBurst_Damage_Near":1800,"mBurst_Damage_Near_Mission":1500,"mBurst_KnockBackCoreImpact":2,"mBurst_KnockBackKb":0.8,"mBurst_KnockBackRadius":90,"mBurst_PaintR":40,"mBurst_Radius_Far":65,"mBurst_Radius_Far_Mission":70,"mBurst_Radius_Near":32.5,"mBurst_Radius_Near_Mission":35,"mBurst_SeFrm":1,"mBurst_SplashAroundFuzzyRate":2,"mBurst_SplashNum":10,"mBurst_SplashOfstY":3,"mBurst_SplashPaintR":7,"mBurst_SplashPitH":30,"mBurst_SplashPitL":5,"mBurst_SplashVelH":3.5,"mBurst_SplashVelL":5.2,"mBurst_WaitFrm":150,"mBurst_WaitFrmNoSearch":60,"mBurst_WarnFrm":60,"mColPlayerOffset":0,"mColPlayerRadius":4,"mCollisionSeSilentFrame":8,"mContactDashPanelAddSpeed":10,"mContactDashPanelAddSpeedVS_SettingOcta_":10,"mContactDashPanelCrossSaveSpeedRate":1,"mContactDashPanelCrossSaveSpeedRateVS_SettingOcta_":1,"mContactJumpPanelAddSpeed":5,"mContactJumpPanelAddSpeedOneBoundRate":0.5,"mContactJumpPanelAddSpeedOneBoundRateVS_":1,"mContactJumpPanelAddSpeedOneBoundRateVS_SettingOcta_":1,"mContactJumpPanelAddSpeedVS_":1,"mContactJumpPanelAddSpeedVS_SettingOcta_":0,"mContactJumpPanelCrossSaveSpeedRate":0.8,"mContactJumpPanelCrossSaveSpeedRateVS_":1,"mContactJumpPanelCrossSaveSpeedRateVS_SettingOcta_":1,"mContactJumpPanelMaxNum":3,"mContactJumpPanelMaxNumVS_":2,"mContactJumpPanelMaxNumVS_SettingOcta_":1,"mContactJumpPanelNrmSaveSpeedRateVS_":1,"mContactJumpPanelNrmSaveSpeedRateVS_SettingOcta_":1,"mContactJumpPanelSpeedLimitVS_":5,"mContactJumpPanelVelKdVS_":0.95,"mCrossPaintRadius":17.5,"mCrossPaintRayLength":17.5,"mCrossPaintRayRadius":1,"mEffectShakeRange":70,"mFly_AirFrm":4,"mFly_Gravity":0.16,"mFly_InitPit":0.4,"mFly_InitRol":0.12,"mFly_ReboundRate":0.7,"mFly_RotI":20,"mFly_RotKd":0.98015,"mFly_VelKd":0.94134,"mInkConsume":0.55,"mInkConsume_Mission":0.7,"mJumpFrame":30,"mModelTargetRotateAxisVelDegree":2,"mModelUpRotateAxisCrossVelDegree":3,"mModelUpRotateAxisVelDegree":1.25,"mPaintRadiusLand":0,"mRotateFrame":10,"mRotateFrame_Mission":30,"mShape_SphereD":5,"mShape_SphereR":2,"mStopChaseDistance":20,"mStopChaseDistanceForDeathPlayer":3,"mStopChaseFrame":60,"mTargetChaseAirAddScaleXZ":0.12,"mTargetChaseAirMaxXZSpeed":0.9,"mTargetChaseAirMaxYSpeed":1.8,"mTargetChaseBaseSpeedComeOverRate":0.2,"mTargetChaseGroundAddScale":0.03,"mTargetChaseGroundMaxSpeed":0.9,"mTargetSearchDownHeight":50,"mTargetSearchForceNoTargetFrame":300,"mTargetSearchNearestDistanceXYZ":true,"mTargetSearchRadius":120,"mTargetSearchUpHeight":50}},"TimerTrap":{"Id":5,"InkSaverType":"D","Name":"TimerTrap","param":{"mBombCoreCrossPaintRadius":25,"mBombCoreCrossPaintRayLength":25,"mBombCoreCrossPaintRayRadius":1,"mBombCoreDamageFar":350,"mBombCoreDamageMiddle":450,"mBombCoreDamageNear":450,"mBombCoreOffsetY":4.5,"mBombCorePaintRadius":50,"mBombCoreRadiusFar":80,"mBombCoreRadiusMiddle":40,"mBombCoreRadiusNear":40,"mBombCoreRadiusRateHigh":1.375,"mBombCoreRadiusRateMid":1.1875,"mConveyerRadius":5,"mExposePaintRate":0.1,"mHalfSphereThresholdY":-5,"mHalfSphereThresholdY2":-15,"mInkConsume":0.6,"mIsAbleToCancelBySquid":true,"mMarkingFrame":300,"mMarkingFrameHigh":600,"mMarkingFrameMid":450,"mMaxHp":1000,"mPaintRadius":10,"mPlayerColRadius":30,"mPlayerColRadiusHigh":40,"mPlayerColRadiusMid":35,"mPresageFrame":45,"mTimerFrame":-1,"mVanishCheckOffsetY":2,"mVanishCheckRadius":3}},"Sprinkler":{"Id":6,"InkSaverType":"D","Name":"Sprinkler","param":{"mBringCloseRateCrossVec":0.7,"mBringCloseRateMoveVec":0.7,"mCol_OffsetY":5,"mCol_Radius":10,"mContactDashPanelAddSpeed_SettingOcta_":10,"mContactDashPanelCrossSaveSpeedRate_SettingOcta_":1,"mConveyerRadius":5,"mDamageRateBias":0.5,"mDamageRateInitial":1,"mDamageRateNormalFrame":450,"mDestroyWaitFrame":0,"mFly_Gravity":0.16,"mFly_InitPit":0.4,"mFly_InitRol":0.12,"mFly_RotI":20,"mFly_RotKd":0.98015,"mFly_VelKd":0.94134,"mGndColOnMovingObj_OffsetY":3,"mGndColOnMovingObj_Radius":3,"mInkConsume":0.6,"mMaxHp":1200,"mObjectDamageRateHigh":10,"mObjectDamageRateMid":10,"mPaintRadius":25,"mPeriod_First":300,"mPeriod_FirstHigh":600,"mPeriod_FirstMid":450,"mPeriod_FirstToSecond":30,"mPeriod_Second":900,"mPeriod_SecondHigh":1020,"mPeriod_SecondMid":960,"mPeriod_SecondToThird":60,"mShape_SphereD":5,"mShape_SphereR":2,"mSleepPlayerDeath":true,"mSpout_RandomDeg":2,"mSpout_RotateMaxSpeedDegree_First":33,"mSpout_RotateMaxSpeedDegree_Second":11,"mSpout_RotateMaxSpeedDegree_Third":1,"mSpout_RotateMaxSpeedFrame":10,"mSpout_Span_First":4,"mSpout_Span_Second":6,"mSpout_Span_Third":10,"mSpout_SplashCollisionR_First":2,"mSpout_SplashCollisionR_Second":2,"mSpout_SplashCollisionR_Third":2,"mSpout_SplashDamage":200,"mSpout_SplashDegBias":0.333,"mSpout_SplashDrawR_First":4,"mSpout_SplashDrawR_Second":4,"mSpout_SplashDrawR_Third":4,"mSpout_SplashPaintR_First":12.5,"mSpout_SplashPaintR_MaxHeight":80,"mSpout_SplashPaintR_MinHeight":200,"mSpout_SplashPaintR_MinRate":0.7,"mSpout_SplashPaintR_Second":11.2,"mSpout_SplashPaintR_Third":10,"mSpout_SplashPitH":55,"mSpout_SplashPitL":35,"mSpout_SplashVelH_First":7,"mSpout_SplashVelH_Second":6.4,"mSpout_SplashVelH_Third":5.6,"mSpout_SplashVelL_First":2.5,"mSpout_SplashVelL_Second":2.2,"mSpout_SplashVelL_Third":1.8,"mSpout_WaitFrame":30}},"PoisonFog":{"Id":7,"InkSaverType":"B","Name":"PoisonFog","param":{"mBringCloseRateCrossVec":0.7,"mBringCloseRateMoveVec":0.7,"mBurstEffectFrame":300,"mBurst_Radius_Far":55,"mBurst_Radius_Middle":54,"mBurst_Radius_Near":55,"mEffectShakeRange":0,"mFly_Gravity":0.16,"mFly_InitPit":0.4,"mFly_InitRol":0.12,"mFly_RotI":20,"mFly_RotKd":0.98015,"mFly_VelKd":0.94134,"mInkConsume":0.6,"mInkConsumeRate":0.05,"mInkRecoverFrame":10,"mLossLv1CycleFrm":60,"mLossLv1Num":3,"mLossLv2CycleFrm":30,"mLossLv2Num":4,"mLossLv3CycleFrm":15,"mPoisonFrame":2,"mShape_SphereD":5,"mShape_SphereR":2,"mSideStepInkConsumeScale":3.5,"mThroughWall":true}},"PointSensor":{"Id":8,"InkSaverType":"B","Name":"PointSensor","param":{"mBringCloseRateCrossVec":0.7,"mBringCloseRateMoveVec":0.7,"mBurstEffectFrame":150,"mBurst_Radius_Far":60,"mBurst_Radius_Far_Start":60,"mBurst_Radius_Middle":59,"mBurst_Radius_Near":60,"mBurst_Radius_ShurinkBias":0.5,"mBurst_Radius_ShurinkFrame":10,"mBurst_Radius_ShurinkStartCount":0,"mEffectShakeRange":0,"mFly_Gravity":0.16,"mFly_InitPit":0.4,"mFly_InitRol":0.12,"mFly_RotI":20,"mFly_RotKd":0.98015,"mFly_VelKd":0.94134,"mInkConsume":0.45,"mMarkingFrame":480,"mMarkingFrameHigh":960,"mMarkingFrameMid":720,"mShape_SphereD":5,"mShape_SphereR":2,"mThroughWall":true}},"Shield":{"Id":9,"InkSaverType":"C","Name":"Shield","param":{"mAirResist":0.001,"mBoundVelLen":3,"mBoundVelY":0.3,"mBoundVelYZeroFrame":5,"mBoundVictroyLiftTiltSuppressMaxDegree":45,"mBoundVictroyLiftTiltSuppressMinDegree":5,"mColCheckBackDistance":0.0001,"mColRadius":5,"mContactDashPanelAddSpeed_SettingOcta_":3,"mContactDashPanelCrossSaveSpeedRate_SettingOcta_":1,"mContactDashPanelHitSpeedMinDirection_SettingOcta_":1.8,"mConveyerRadius":5,"mDamage":300,"mDamageForEnemy":300,"mDamageSpanFrameForObj":30,"mDestroyWaitFrame":15,"mDrawRadius":1,"mGndColOnMovingObj_OffsetY":3,"mGndColOnMovingObj_Radius":3,"mGravity":0.09,"mGroundVictroyLiftBoundInDegree":18,"mGroundVictroyLiftBoundNum":1,"mGroundVictroyLiftBoundOutDegree":18,"mGroundVictroyLiftBoundSpeedRate":1,"mHitEffectLimitSpanFrame":8,"mImpactScaleForEnemy":1,"mInkConsume":0.6,"mLengthBullet":[45,40,5],"mLengthCommon":[45,40,5],"mMaxHp":8000,"mMaxHpHigh":15000,"mMaxHpMid":11500,"mMinimumSetToPrepareFrame":5,"mMinimumSetToRunStartFrameReceive":25,"mMinimumThrowToRunStartFrame":55,"mNoBulletDamageMission":true,"mNoDamageRunningDurationFrame":400,"mObjectDamageRateHigh":1.5,"mObjectDamageRateMid":1.5,"mPaintLength":55,"mPaintMoveSphereCheckOffsetX":30,"mPaintMoveSphereCheckOffsetY":40,"mPaintRepeatFrame":6,"mPaintWidth":10,"mPreparationDurationFrameMission":20,"mPrepareAnimStretchFrame":10,"mRejectDebugDraw":false,"mRejectDepthMax":6,"mRejectDepthMin":3,"mRejectLength":[50,40,30],"mRejectMagHumanFall":0.2,"mRejectMagHumanH":1,"mRejectMagHumanJump":0.2,"mRejectMagHumanL":0.2,"mRejectMagShotH":1,"mRejectMagShotL":0.2,"mRejectMagSquidFall":0.1,"mRejectMagSquidH":0.1,"mRejectMagSquidJump":0,"mRejectMagSquidL":0,"mRejectNetFakeJump":0.7,"mRejectNetFakeJumpGap":1,"mRejectNetReceivNoEffect":false,"mRejectSpeedRtBias":0.7,"mRejectStickDownHuman":1,"mRejectStickDownHumanFall":0.8,"mRejectStickDownHumanJump":0.8,"mRejectStickDownSquid":0.8,"mRejectStickDownSquidFall":0.8,"mRejectStickDownSquidJump":0,"mRejectUnderWalkRadius":5,"mTransformPlayFrameBeforeRunning":30,"mVLiftCheck_GapBottom":2.5,"mVLiftCheck_GapSide":0,"mVLiftCheck_GapTop":0,"mVLiftCheck_Radius":2.5,"mWallCrossBoundRate":0.99,"mWallCrossBoundRateVictoryLiftNormal":0.99,"mWallNrmBoundRate":0.3,"mWallNrmBoundRateVictoryLiftNormal":0.8}},"Flag":{"Id":10,"InkSaverType":"D","Name":"Flag","param":{"mColHeight":15,"mColRadius":5,"mConveyerRadius":5,"mDestroyWaitFrame":0,"mGndColOnMovingObj_OffsetY":3,"mGndColOnMovingObj_Radius":3,"mImmediateDestroyDamage":99999,"mImmediateDestroyDamageThreshold":99900,"mInkConsume":0.75,"mMapFoundDistance":150,"mMaxHp":1200,"mNoPlaceDistance":8,"mObjectDamageRateHigh":10,"mObjectDamageRateMid":10,"mPaintRadius":10,"mSubRt_Effect_ActualCnt_High":57,"mSubRt_Effect_ActualCnt_Low":0,"mSubRt_Effect_ActualCnt_Mid":25,"mThermalDistance":-1,"mWarpDestroyDamage":10000,"mWarpDestroyDamageThreshold":9900,"mWarpDestroyNum":2,"mWarpDestroyWaitFrame":5}},"Bomb_Piyo":{"Id":11,"InkSaverType":"B","Name":"Bomb_Piyo","param":{"mBringCloseRateCrossVec":0.7,"mBringCloseRateMoveVec":0.7,"mBurst_Damage_Far_Cnt0":350,"mBurst_Damage_Far_Cnt1":350,"mBurst_Damage_Far_Cnt2":350,"mBurst_Damage_Near_Cnt0":500,"mBurst_Damage_Near_Cnt1":500,"mBurst_Damage_Near_Cnt2":500,"mBurst_KnockBackCoreImpact_Cnt0":2,"mBurst_KnockBackCoreImpact_Cnt1":2,"mBurst_KnockBackCoreImpact_Cnt2":2,"mBurst_KnockBackKb_Cnt0":0.8,"mBurst_KnockBackKb_Cnt1":0.8,"mBurst_KnockBackKb_Cnt2":0.8,"mBurst_KnockBackRadius_Cnt0":80,"mBurst_KnockBackRadius_Cnt1":80,"mBurst_KnockBackRadius_Cnt2":80,"mBurst_PaintR_Cnt0":30,"mBurst_PaintR_Cnt1":34,"mBurst_PaintR_Cnt2":38,"mBurst_Radius_Far_Cnt0":38,"mBurst_Radius_Far_Cnt1":45,"mBurst_Radius_Far_Cnt2":54.5,"mBurst_Radius_Near_Cnt0":20,"mBurst_Radius_Near_Cnt1":23.5,"mBurst_Radius_Near_Cnt2":30,"mBurst_SeFrm_Cnt0":10,"mBurst_SeFrm_Cnt1":7,"mBurst_SeFrm_Cnt2":7,"mBurst_SplashAroundFuzzyRate_Cnt0":0.5,"mBurst_SplashAroundFuzzyRate_Cnt1":0.5,"mBurst_SplashAroundFuzzyRate_Cnt2":0.5,"mBurst_SplashNum_Cnt0":6,"mBurst_SplashNum_Cnt1":6,"mBurst_SplashNum_Cnt2":6,"mBurst_SplashOfstY_Cnt0":3,"mBurst_SplashOfstY_Cnt1":3,"mBurst_SplashOfstY_Cnt2":3,"mBurst_SplashPaintR_Cnt0":7,"mBurst_SplashPaintR_Cnt1":7,"mBurst_SplashPaintR_Cnt2":7,"mBurst_SplashPitH_Cnt0":25,"mBurst_SplashPitH_Cnt1":20,"mBurst_SplashPitH_Cnt2":20,"mBurst_SplashPitL_Cnt0":10,"mBurst_SplashPitL_Cnt1":10,"mBurst_SplashPitL_Cnt2":10,"mBurst_SplashVelH_Cnt0":4,"mBurst_SplashVelH_Cnt1":4.2,"mBurst_SplashVelH_Cnt2":4.3,"mBurst_SplashVelL_Cnt0":3.5,"mBurst_SplashVelL_Cnt1":3.6,"mBurst_SplashVelL_Cnt2":3.9,"mBurst_WaitFrm_Cnt0":15,"mBurst_WaitFrm_Cnt1":1,"mBurst_WaitFrm_Cnt2":1,"mBurst_WarnFrm_Cnt0":15,"mBurst_WarnFrm_Cnt1":7,"mBurst_WarnFrm_Cnt2":7,"mCharge_DecrFramePerGachaGyro":9,"mCharge_DecrFramePerGachaJump":8,"mCharge_DecrFramePerGachaStick":11,"mCharge_FrameTo2":40,"mCharge_FrameTo3":80,"mCharge_GachaFrameBuffer":30,"mCharge_GachaFramePerOneFrame":2.5,"mCollisionSeSilentFrame":4,"mCollisionSeVelDotGndNrm":0.08,"mCollisionSeVelDotGndTimes":1.2,"mContactDashPanelAddSpeed":9.5,"mContactDashPanelCrossSaveSpeedRate":0.9,"mContactJumpPanelAddSpeedOneBoundRateVS_":1,"mContactJumpPanelAddSpeedVS_":2,"mContactJumpPanelCrossSaveSpeedRateVS_":1,"mContactJumpPanelMaxNumVS_":2,"mContactJumpPanelNrmSaveSpeedRateVS_":1,"mContactJumpPanelSpeedLimitVS_":5,"mContactJumpPanelVelKdVS_":1,"mCrossPaintRadius":20,"mCrossPaintRayLength":20,"mCrossPaintRayRadius":1,"mDamageHitRailPoint":100,"mEffectShakeRange":70,"mFlySplash_ColRadius":1.5,"mFlySplash_Distance_Ch0":22,"mFlySplash_Distance_Ch1":22,"mFlySplash_Distance_Ch2":22,"mFlySplash_Distance_First":0,"mFlySplash_DrawRadius":1,"mFlySplash_MaxScaleClamp_Ch0":1.6,"mFlySplash_MaxScaleClamp_Ch1":1.6,"mFlySplash_MaxScaleClamp_Ch2":1.6,"mFlySplash_MaxScaleHighest_Ch0":30,"mFlySplash_MaxScaleHighest_Ch1":30,"mFlySplash_MaxScaleHighest_Ch2":30,"mFlySplash_MinScaleClamp_Ch0":1.6,"mFlySplash_MinScaleClamp_Ch1":1.6,"mFlySplash_MinScaleClamp_Ch2":1.6,"mFlySplash_MinScaleHighest_Ch0":100,"mFlySplash_MinScaleHighest_Ch1":100,"mFlySplash_MinScaleHighest_Ch2":100,"mFlySplash_PaintRadius_Ch0":9,"mFlySplash_PaintRadius_Ch1":10,"mFlySplash_PaintRadius_Ch2":11,"mFlySplash_Vel":1,"mFly_AirFrm":4,"mFly_CeilingKf_Y":1,"mFly_CeilingKr_Y":0.5,"mFly_Gravity":0.16,"mFly_InitPit":0.4,"mFly_InitRol":0.12,"mFly_RotI":20,"mFly_RotKd":0.98015,"mFly_VelKd":0.94134,"mFly_WallKf_XZ":0.7,"mFly_WallKf_Y":0.2,"mFly_WallKr":0.2,"mForceSleepFrame":900,"mFrameIntervalForceBurst":10,"mGachaAnimFrame":30,"mHop_PitchH":45,"mHop_PitchL":35,"mHop_VelH":4,"mHop_VelL":3,"mHop_YawH":30,"mHop_YawL":-30,"mInkConsume":0.6,"mIntervalBurst":16,"mIntervalHitRailPoint":20,"mLand_AbsorveRt":0.1,"mLand_GndKf":0.2,"mLand_GndKr":0.05,"mLand_GravGndK":0.5,"mLand_GravH":0.08,"mLand_GravKf":0.1,"mLand_GravL":0.016,"mLand_NrmGndKf":0.1,"mLand_RotI":10,"mLand_RotKd":0.96059,"mLand_VelKdXZ":0.92237,"mLand_VelKdY":0.92237,"mMaxPitchHop":70,"mMinPitchHop":-20,"mShape_SphereD":5,"mShape_SphereR":2}},"Bomb_Tako":{"Id":12,"InkSaverType":"C","Name":"Bomb_Tako","param":{"mAccel":0.5,"mAngleCorrectDir":0,"mBringCloseRateCrossVec":0.7,"mBringCloseRateMoveVec":0.7,"mBurst_Damage_Far":350,"mBurst_Damage_Near":600,"mBurst_KnockBackCoreImpact":1,"mBurst_KnockBackKb":0.8,"mBurst_KnockBackRadius":120,"mBurst_PaintR":35,"mBurst_Radius_Far":60,"mBurst_Radius_Near":30,"mBurst_SeFrm":1,"mBurst_SplashAroundFuzzyRate":0,"mBurst_SplashNum":8,"mBurst_SplashOfstY":5,"mBurst_SplashPaintR":20,"mBurst_SplashPitH":65,"mBurst_SplashPitL":65,"mBurst_SplashVelH":4.8,"mBurst_SplashVelL":4.2,"mBurst_WaitFrm":0,"mBurst_WarnFrm":30,"mChaseCheckColRadius":5,"mChaseDistanceMax":90,"mChaseDistanceMin":25,"mChaseDistanceYMinus":-20,"mChaseDistanceYPlus":30,"mColRadiusVsBullet":7,"mColRadiusVsPlayer":6,"mCollisionSeSilentFrame":8,"mCollisionSeVelDotGndNrm":0.08,"mCollisionSeVelDotGndTimes":1.2,"mContactDashPanelAddSpeed":9.5,"mContactDashPanelCrossSaveSpeedRate":0.9,"mContactJumpPanelAddSpeed":2,"mContactJumpPanelAddSpeedOneBoundRate":1,"mContactJumpPanelCrossSaveSpeedRate":1,"mContactJumpPanelMaxNum":2,"mContactJumpPanelNrmSaveSpeedRate":1,"mContactJumpPanelSpeedLimit":5,"mContactJumpPanelVelKd":1,"mConveyer_Radius":5,"mCrossPaintRadius":20,"mCrossPaintRayLength":20,"mCrossPaintRayRadius":1,"mDamageRateObjectEffectUp":1.3,"mDelayFrameColPlayer":25,"mEffectShakeRange":100,"mFly_AirFrm":4,"mFly_CeilingKf_Y":1,"mFly_CeilingKr_Y":0.5,"mFly_Gravity":0.16,"mFly_InitPit":0.4,"mFly_InitRol":0.12,"mFly_RotI":100,"mFly_RotKd":0.98015,"mFly_VelKd":0.94134,"mFly_WallKf_XZ":0.7,"mFly_WallKf_Y":0.2,"mFly_WallKr":0.2,"mFoot_ColR":2,"mFoot_DrawR":2,"mFoot_Gravity":0.5,"mFoot_OffsetZ":-3,"mFoot_PaintR":27,"mFoot_PaintScaleY":1.7,"mFrameChase":150,"mFrameNoCollision":5,"mFrameOmen":60,"mInkConsume":0.65,"mLand_AbsorveRt":0.1,"mLand_GndKf":0.2,"mLand_GndKr":0.05,"mLand_GravGndK":0.5,"mLand_GravH":0.08,"mLand_GravKf":0.1,"mLand_GravL":0.016,"mLand_NrmGndKf":0.1,"mLand_RotI":10,"mLand_RotKd":0.96059,"mLand_VelKdXZ":0.92237,"mLand_VelKdY":0.92237,"mLife":200,"mLock_DelayFrame":5,"mLock_FallColR":1,"mLock_FallDrawR":2,"mLock_FallPaintR":20,"mLock_SplashAroundFuzzyRate":2,"mLock_SplashNum":6,"mLock_SplashOfstY":5,"mLock_SplashPaintR":7,"mLock_SplashPitH":45,"mLock_SplashPitL":30,"mLock_SplashVelH":2.3,"mLock_SplashVelL":1.5,"mMaxSpeed_Chase":2,"mNC_Burst_Damage_Far":350,"mNC_Burst_Damage_Near":600,"mNC_Burst_KnockBackCoreImpact":3,"mNC_Burst_KnockBackKb":0.8,"mNC_Burst_KnockBackRadius":120,"mNC_Burst_PaintR":35,"mNC_Burst_Radius_Far":60,"mNC_Burst_Radius_Near":30,"mNC_Burst_SplashAroundFuzzyRate":2,"mNC_Burst_SplashNum":0,"mNC_Burst_SplashOfstY":5,"mNC_Burst_SplashPaintR":6,"mNC_Burst_SplashPitH":45,"mNC_Burst_SplashPitL":5,"mNC_Burst_SplashVelH":3.5,"mNC_Burst_SplashVelL":3,"mNC_CrossPaintRadius":20,"mNC_CrossPaintRayLength":20,"mNC_CrossPaintRayRadius":1,"mPrepareFloatLength":3,"mPrepareFloatSpeed":0.1,"mPrepare_LockOn":15,"mPrepare_RotMaxAngle":160,"mPrepare_RotMaxFrame":20,"mPrepare_Transform":25,"mScaleBias":0.5,"mScaleInit":1.8,"mScaleMax":1.4,"mShape_SphereD":5,"mShape_SphereR":2,"mShape_SphereR_Max":6,"mShotKnockbackMagnitude":0,"mShotKnockbackStickDownRt":5,"mSplashBurst_ColRadius":2,"mSplashBurst_CrossPaintRadius":10,"mSplashBurst_CrossPaintRayLength":10,"mSplashBurst_CrossPaintRayRadius":1,"mSplashBurst_Damage":120,"mSplashBurst_DamageRadius":30,"mSplashBurst_DrawRadius":3,"mSplashBurst_EmitInterval":2,"mSplashBurst_KnockBackCoreImpact":0,"mSplashBurst_KnockBackKb":0.5,"mSplashBurst_KnockBackRadius":0,"mSplashBurst_RotDegEachSplashAxisY":135}}},"specials":{"SuperMissile":{"Id":0,"Name":"SuperMissile","param":{"mApproachBaseSpeed":5,"mApproachBaseSpeedComeOverRate":0.92,"mApproachBaseSpeedComeUnderRate":0.96,"mApproachBaseSpeedVsOnlyOneTarget":4,"mApproachRotateDegreeMax":4,"mApproachStartBaseSpeed":2,"mApproachStartBaseSpeedComeOverRate":0.65,"mApproachStartBaseSpeedComeUnderRate":0.8,"mApproachStartRotateDegreeMax":4,"mApproachStartStateFrame":15,"mApproachStateMissileMaxDegree":45,"mApproachStateTargetDistanceXZ":60,"mApproachStateTargetDistanceXZAddLockOn":0,"mApproachStateTargetDistanceXZAddOneTarget":10,"mApproachStateTargetDistanceXZAddOneTargetVsOnlyOneTarget":0,"mApproachStateTargetDistanceXZVsOnlyOneTarget":75,"mApproachStateTargetHeight":110,"mApproachStateTargetHeightAddLockOn":0,"mApproachStateTargetHeightAddOneTarget":10,"mApproachStateTargetHeightAddOneTargetVsOnlyOneTarget":0,"mApproachStateTargetHeightVsOnlyOneTarget":125,"mApproachStateTargetMaxDegree":20,"mApproachStateTargetMinDegree":0,"mApproachWaitBaseSpeed":0.001,"mApproachWaitBaseSpeedComeOverRate":0.01,"mApproachWaitBaseSpeedComeUnderRate":0.01,"mApproachWaitInterval":8,"mApproachWaitIntervalVS":6,"mApproachWaitRotateDegreeMax":0,"mBringCloseRateCrossVec":0.93,"mBringCloseRateMoveVec":0.93,"mBulletThrough":false,"mBurst_Damage_Far":300,"mBurst_Damage_Middle":500,"mBurst_Damage_Near":1500,"mBurst_PaintR":30,"mBurst_PaintRHigh":36,"mBurst_PaintRMid":33,"mBurst_Radius_Far":50,"mBurst_Radius_Middle":25,"mBurst_Radius_Near":15,"mChaseBaseSpeed":4.2,"mChaseBaseSpeedComeOverRate":0.01,"mChaseBaseSpeedComeUnderRate":0.01,"mChaseDegreeHorizonMinA":12,"mChaseDegreeHorizonMinB":2,"mChaseRotateDegreeMax":0,"mChaseStartBaseSpeed":0.01,"mChaseStartBaseSpeedComeOverRate":0.01,"mChaseStartBaseSpeedComeUnderRate":0.01,"mChaseStartRotateDegreeMax":0,"mChaseStartStateFrame":25,"mCollisionRadius":1.5,"mCoopBurst_Damage_Far":150,"mCoopBurst_Damage_Middle":300,"mCoopBurst_Damage_Near":500,"mCoopBurst_PaintR":40,"mCoopBurst_Radius_Far":50,"mCoopBurst_Radius_Middle":25,"mCoopBurst_Radius_Near":15,"mCoopCrossPaintRadius":20,"mCoopCrossPaintRayLength":30,"mCoopDamage":1500,"mCrossPaintRadius":20,"mCrossPaintRadiusHigh":20,"mCrossPaintRadiusMid":20,"mCrossPaintRayLength":30,"mCrossPaintRayLengthHigh":30,"mCrossPaintRayLengthMid":30,"mCrossPaintRayRadius":1,"mCurveBaseSpeed":1,"mCurveBaseSpeedComeOverRate":0.8,"mCurveBaseSpeedComeUnderRate":0.8,"mCurveMaxSpeedY":2,"mCurveRotateDegreeMax":3,"mCurveStateMaxFrame":60,"mCurveStateMinFrame":10,"mCurveStateNextStateMinDegreeAxisX":0.01,"mCurveStateNextStateMinDegreeAxisY":0.01,"mDamage":1500,"mKnockBackCoreImpact":3,"mKnockBackKb":0.8,"mKnockBackNoBarrierOff":false,"mKnockBackRadius":80,"mOccurOffset":5,"mPaintGauge_JumpGnd_Preparing":0,"mPaintGauge_JumpGnd_Searching":0.6,"mPaintGauge_JumpGnd_Shooting":0,"mPaintGauge_PointFull":180,"mPaintGauge_SpecialFrm":600,"mPaintGauge_VelGnd_Preparing":0,"mPaintGauge_VelGnd_Searching":0.48,"mPaintGauge_VelGnd_Shooting":0,"mPlayerTargetCircle1NumVsOnlyOneTarget":1,"mPlayerTargetCircle1RadiusVsOnlyOneTarget":0,"mPlayerTargetCircle1RandomOffsetZXVsOnlyOneTarget":0,"mPlayerTargetCircle2NumVsOnlyOneTarget":9,"mPlayerTargetCircle2RadiusVsOnlyOneTarget":30,"mPlayerTargetCircle2RandomOffsetZXVsOnlyOneTarget":5,"mPlayerTargetCircle3RadiusVsOnlyOneTarget":50,"mPlayerTargetCircle3RandomOffsetZXVsOnlyOneTarget":5,"mPlayerTargetCircleXRandomOffsetBiasVsOnlyOneTarget":0.35,"mPlayerTargetEffectDegree":90,"mPlayerTargetEffectDirectionSolid":true,"mPlayerTargetEffectState":5,"mPlayerTargetHitCollisionLoopNum":5,"mPlayerTargetRandomOffsetBias":0.3,"mPlayerTargetRandomOffsetXZ":40,"mPlayerTargetSolidDistanceXZ":1000,"mPlayerTargetSolidState":4,"mRiseBaseSpeed":4,"mRiseBaseSpeedComeOverRate":0.9,"mRiseBaseSpeedComeUnderRate":0.9,"mRiseInitialSpeed":4,"mRiseMinHeight":76,"mRiseMinHeightAddLockOn":0,"mRiseMinHeightAddOneTarget":10,"mRiseMinHeightAddOneTargetVsOnlyOneTarget":0,"mRiseMinHeightVsOnlyOneTarget":90,"mRiseTargetPlayerOverHeight":56,"mRiseTargetPlayerOverHeightAddLockOn":0,"mRiseTargetPlayerOverHeightAddOneTarget":10,"mRiseTargetPlayerOverHeightAddOneTargetVsOnlyOneTarget":0,"mRiseTargetPlayerOverHeightVsOnlyOneTarget":70,"mShotInsideDegree":0.1,"mShotIntervalAround":0,"mShotIntervalTarget1":8,"mShotIntervalTarget1VsOnlyOneTarget":4,"mShotIntervalTarget2":4,"mShotIntervalTarget3":4,"mShotIntervalTarget4":4,"mShotIntervalTargetMission":8,"mShotNumOneTarget1":4,"mShotNumOneTarget1VsOnlyOneTarget":10,"mShotNumOneTarget2":5,"mShotNumOneTarget3":4,"mShotNumOneTarget4":4,"mShotNumOneTargetMission":4,"mShotOutsideDegree":12,"mStartCollisionCheckState":6,"mSuperJumpDecideFrame":95,"mTargetCircleCenterOffset":[0,65],"mTargetCircleEffectDefaultRadius":93,"mTargetInCircleRadius":140,"mTargetInCircleRadiusHigh":240,"mTargetInCircleRadiusMid":190,"mTargetOutCircleAddRadius":30,"mTargetOutCircleFrame":20,"mTargetPlayerLockOnCount":5,"mTargetPlayerLockOnSeFrame":3}},"SuperArmor":{"Id":1,"Name":"SuperArmor","param":{"mBreakAfterglowFrm":12,"mEnergyAbsorbFrm":90,"mEnergyAbsorbFrmH":30,"mEnergyAbsorbFrmM":60,"mFinishNoticeFrm":180,"mInvokeMotion_Frm":30,"mInvokeMotion_JumpGnd":0,"mInvokeMotion_NoSquidFrm":40,"mInvokeMotion_VelGnd":0,"mMaxDamageInPlayer":800,"mMoveDistH":600,"mMoveFrmH":30,"mMoveFrmL":10,"mObjectEffect_Up_DamageRt_High":3,"mObjectEffect_Up_DamageRt_Low":1,"mObjectEffect_Up_DamageRt_Mid":3,"mObjectEffect_Up_WaterCutter_DamageRt_High":1.25,"mObjectEffect_Up_WaterCutter_DamageRt_Low":1,"mObjectEffect_Up_WaterCutter_DamageRt_Mid":1.25,"mOverDamageInPlayer":1000,"mPaintGauge_PointFull":180,"mPaintGauge_SpecialFrm":360,"mPaintGauge_SpecialFrmH":540,"mPaintGauge_SpecialFrmM":450}},"LauncherSplash":{"Id":2,"Name":"LauncherSplash","param":{"mChargeFrmH":20,"mChargeFrmL":0,"mDelayFrm_Squid":10,"mPaintGauge_PointFull":180,"mPaintGauge_SpecialFrm":360,"mPaintGauge_SpecialFrmH":480,"mPaintGauge_SpecialFrmM":420,"mShotSpanFrm":30,"mSpeedB":0.5,"mSpeedH":18,"mSpeedL":9.5,"mUnrelaxFrmNoBomb":60}},"LauncherSuction":{"Id":3,"Name":"LauncherSuction","param":{"mChargeFrmH":20,"mChargeFrmL":0,"mDelayFrm_Squid":10,"mPaintGauge_PointFull":180,"mPaintGauge_SpecialFrm":360,"mPaintGauge_SpecialFrmH":480,"mPaintGauge_SpecialFrmM":420,"mShotSpanFrm":30,"mSpeedB":0.5,"mSpeedH":18,"mSpeedL":9.5,"mUnrelaxFrmNoBomb":60}},"LauncherQuick":{"Id":4,"Name":"LauncherQuick","param":{"mChargeFrmH":15,"mChargeFrmL":0,"mDelayFrm_Squid":10,"mPaintGauge_PointFull":180,"mPaintGauge_SpecialFrm":360,"mPaintGauge_SpecialFrmH":480,"mPaintGauge_SpecialFrmM":420,"mShotSpanFrm":20,"mSpeedB":0.5,"mSpeedH":18,"mSpeedL":9.5,"mUnrelaxFrmNoBomb":60}},"LauncherCurling":{"Id":5,"Name":"LauncherCurling","param":{"mChargeFrmH":20,"mChargeFrmL":0,"mDelayFrm_Squid":10,"mPaintGauge_PointFull":180,"mPaintGauge_SpecialFrm":400,"mPaintGauge_SpecialFrmH":520,"mPaintGauge_SpecialFrmM":460,"mShotSpanFrm":30,"mSpeedB":0.5,"mSpeedH":16.8,"mSpeedL":11.2,"mUnrelaxFrmNoBomb":60}},"LauncherRobo":{"Id":6,"Name":"LauncherRobo","param":{"mChargeFrmH":20,"mChargeFrmL":0,"mDelayFrm_Squid":10,"mPaintGauge_PointFull":180,"mPaintGauge_SpecialFrm":360,"mPaintGauge_SpecialFrmH":480,"mPaintGauge_SpecialFrmM":420,"mShotSpanFrm":30,"mSpeedB":0.5,"mSpeedH":18,"mSpeedL":9.5,"mUnrelaxFrmNoBomb":60}},"WaterCutter":{"Id":7,"Name":"WaterCutter","param":{"mCollisionFieldRadius":4,"mCollisionPlayerExpansionStartFrame":90,"mCollisionPlayerExpansioningFrame":45,"mCollisionPlayerRadius":7,"mCollisionPlayerRadius_Expansion":14,"mDamageCoopEnemy":10,"mDamageCoopPlayer":18,"mDamageMax":18,"mDamageMaxDistance":500,"mDamageMinDistance":1000,"mDamageMinRate":1,"mDamageRateFieldBehindAddOrScale":-1,"mDamageRateFieldBehindAddOrScaleType":0,"mDamageRateMinFieldBehind":0.84,"mDrainKeepFrm":0,"mEffectXZScale":5,"mKnockBackAquaBallPlayerImpact":0.08,"mLength":2832,"mPaintGauge_JumpGnd":0.6,"mPaintGauge_PointFull":180,"mPaintGauge_ShotDirXZ_DiffDegH":20,"mPaintGauge_ShotDirXZ_DiffDegL":0,"mPaintGauge_ShotDirXZ_RevKf":0.05,"mPaintGauge_ShotDirXZ_RotDegBias":0.4,"mPaintGauge_ShotDirXZ_RotDegH":0.18,"mPaintGauge_ShotDirXZ_RotDegH_Expansion":0.18,"mPaintGauge_ShotDirXZ_RotDegL":0,"mPaintGauge_ShotDir_RevBias":0.4,"mPaintGauge_ShotDir_RevFrm":90,"mPaintGauge_ShotPitchRt_RevKf":0.05,"mPaintGauge_ShotPitchRt_Vel":0.0025,"mPaintGauge_ShotPitchRt_Vel_Expansion":0.0025,"mPaintGauge_SpecialFrm":430,"mPaintGauge_SpecialFrmH":510,"mPaintGauge_SpecialFrmM":470,"mPaintGauge_VelGnd":0.3,"mPaintOverPreventionDistance":1000,"mPaintOverPreventionGroundAndPrevGroundDegree":10,"mPaintOverPreventionVelAndGroundDegree":20,"mPaintRadius":20,"mPaintRadiusAddOrScale":-10,"mPaintRadiusAddOrScaleType":0,"mPaintRadiusMin":10,"mReceiverHitEffectFrame":8,"mRespawnPointReject_Enable":true,"mRespawnPointReject_Impact":0.1,"mRespawnPointReject_Reject":0.96,"mRespawnPointReject_StickDownRt":10,"mStartPosBackOffsetLength":7.5,"mThermalInkKeepFrm":180,"mUnsendElementUseRate":0.75,"mWaitFrame":30,"mbSilhouetteEnable":true}},"Jetpack":{"Id":8,"Name":"Jetpack","param":{"mAirMoveLmt_Frm":120,"mBombCoreRadiusRateHigh":1.3,"mBombCoreRadiusRateMid":1.15,"mBoost_JumpVel":2,"mBoost_NoBoostFrm":90,"mBoost_NoSquidFrm":30,"mBurst_KnockBackCoreImpact":2,"mBurst_KnockBackKb":0.6,"mBurst_KnockBackRadius":80,"mBurst_PaintR":32,"mBurst_PaintRHigh":40,"mBurst_PaintRMid":36,"mBurst_SplashAroundFuzzyRate":2,"mBurst_SplashNum":10,"mBurst_SplashOfstY":3,"mBurst_SplashPaintR":6.3,"mBurst_SplashPaintRHigh":7,"mBurst_SplashPaintRMid":6.65,"mBurst_SplashPitH":30,"mBurst_SplashPitL":5,"mBurst_SplashVelH":3.3,"mBurst_SplashVelHHigh":3.5,"mBurst_SplashVelHMid":3.4,"mBurst_SplashVelL":4.9,"mBurst_SplashVelLHigh":5.2,"mBurst_SplashVelLMid":5.05,"mColRadius":3,"mCollisionRadiusFar":50,"mCollisionRadiusMiddle":25,"mCollisionRadiusNear":25,"mDamage":1200,"mDamageFar":300,"mDamageMiddle":500,"mDamageNear":500,"mDamagePlayer":1200,"mDistance":300,"mDrawRadius":1.5,"mGuideCheckCollisionFrame":40,"mGuideDrawLine":false,"mInitVel":7.5,"mJetFootDamageAndPaintHeight":100,"mJetFootDamagePerFrame":5,"mJetFootDamageRadius":10,"mJetFootPaintCollisionRadius":2,"mJetFootPaintRadius":12,"mJetFootTiltCalcHeight":10,"mJetpackPointEffect_GaugeFrm":80,"mJumpAfterFrm":24,"mKnockBackRate":5,"mMove_Acc_SettingOcta_":0.1,"mMove_Brk_SettingOcta_":0.02,"mMove_Trn_SettingOcta_":0.4,"mMove_VelGnd_Kf_SettingOcta_":0.03,"mMove_VelScale_SettingOcta_":1,"mPaintGauge_PointFull":180,"mPaintGauge_SpecialFrm":450,"mPaintGauge_SpecialFrmH":510,"mPaintGauge_SpecialFrmM":480,"mRepeatFrame":60,"mRiseFall_AltitudeCheck_Dist":200,"mRiseFall_AltitudeCheck_Num":16,"mRiseFall_AltitudeCheck_OfstY":1,"mRiseFall_AltitudeCheck_SphereR":3,"mRiseFall_Altitude_Kf_D":1,"mRiseFall_Altitude_Kf_U":1,"mRiseFall_CruiseAltitude_SettingOcta_":40,"mRiseFall_FallAcc":0.02,"mRiseFall_NoJumpAirFrm":120,"mRiseFall_PID_Kd":0.0067,"mRiseFall_PID_Kd_AfterBoost":0.0134,"mRiseFall_PID_Ki":0.042,"mRiseFall_PID_Ki_AfterBoost":0.042,"mRiseFall_PID_Kp":0.05,"mRiseFall_PID_Kp_AfterBoost":0.05,"mRiseFall_PID_ResetWindup":10,"mRiseFall_RiseAcc":0.2,"mRiseFall_RiseDelayFrm_ToHuman":15,"mRiseFall_RiseVel":2.15,"mRiseFall_SquidAccRtDamp_Bias":0.5,"mRiseFall_SquidAccRtDamp_Frm":13,"mRiseFall_ToSquid_GravityDownBias":0.5,"mRiseFall_ToSquid_GravityDownEn":1,"mRiseFall_ToSquid_GravityDownFrm":20,"mRiseFall_ToSquid_GravityDownSt":0.2,"mShotDelayFrm":50,"mShotDelayFrm_Req":10}},"SuperLanding":{"Id":9,"Name":"SuperLanding","param":{"mBurst_CapsuleHeight":40,"mBurst_CapsuleHeight_SJ":40,"mBurst_Damage_Far":550,"mBurst_Damage_Far_SJ":550,"mBurst_Damage_HalfSphereThresholdY":-45,"mBurst_Damage_HalfSphereThresholdY_SJ":-45,"mBurst_Damage_Middle":700,"mBurst_Damage_Middle_SJ":700,"mBurst_Damage_Near":1800,"mBurst_Damage_Near_SJ":1800,"mBurst_KnockBackCoreImpact":4.2,"mBurst_KnockBackCoreImpact_SJ":4.2,"mBurst_KnockBackKb":0.5,"mBurst_KnockBackKb_SJ":0.5,"mBurst_KnockBackRadius":150,"mBurst_KnockBackRadius_SJ":150,"mBurst_Landing_AddHeight_High":40,"mBurst_Landing_AddHeight_Mid":20,"mBurst_Landing_AddHeight_SJ_High":40,"mBurst_Landing_AddHeight_SJ_Mid":20,"mBurst_Landing_Height":20,"mBurst_Landing_Height_H":100,"mBurst_Landing_Height_SJ":20,"mBurst_Landing_Height_SJ_H":100,"mBurst_Offset":10,"mBurst_Offset_SJ":10,"mBurst_PaintR":130,"mBurst_PaintR_SJ":130,"mBurst_Radius_Far":140,"mBurst_Radius_Far_H":140,"mBurst_Radius_Far_SJ":140,"mBurst_Radius_Far_SJ_H":140,"mBurst_Radius_Middle":100,"mBurst_Radius_Middle_H":125,"mBurst_Radius_Middle_SJ":112.5,"mBurst_Radius_Middle_SJ_H":112.5,"mBurst_Radius_Near":70,"mBurst_Radius_Near_H":110,"mBurst_Radius_Near_SJ":90,"mBurst_Radius_Near_SJ_H":90,"mCrossPaintEllipticRate":2,"mCrossPaintEllipticRate_SJ":1,"mCrossPaintRadius":40,"mCrossPaintRadius_SJ":60,"mCrossPaintRayLength":60,"mCrossPaintRayLength_SJ":60,"mCrossPaintRayRadius":1,"mCrossPaintRayRadius_SJ":1,"mLand_MotionFrm":10,"mLand_NoDamageFrm":30,"mPaintGauge_PointFull":180,"mPaintGauge_SpecialFrm":480,"mRayCheckRadius":5.25,"mRise_NoDamageFrm":5}},"RainCloud":{"Id":10,"Name":"RainCloud","param":{"mBringCloseRateCrossVec":0.7,"mBringCloseRateMoveVec":0.7,"mEffectShakeRange":0,"mFly_Gravity":0.16,"mFly_InitPit":0.4,"mFly_InitRol":0.12,"mFly_RotI":20,"mFly_RotKd":0.98015,"mFly_VelKd":0.94134,"mKnockBackCoreImpact":3,"mKnockBackKb":0.8,"mKnockBackNoBarrierOff":true,"mKnockBackRadius":85,"mNoPaintRainDropsTotalNum":120,"mPaintGauge_PointFull":180,"mPaintGauge_SpecialFrm":600,"mRainAreaDamagePerFrame":4,"mRainAreaFrame":480,"mRainAreaFrameHigh":600,"mRainAreaFrameMid":540,"mRainAreaHeight":300,"mRainAreaMoveSpeed":0.6,"mRainAreaMoveWaitFrame":30,"mRainAreaRadius":85,"mRainAreaRadiusMax":85,"mRainAreaRadiusRateHigh":1,"mRainAreaRadiusRateMid":1,"mRainAreaSpreadHeightWaitFrame":0,"mRainDropsAirResist":0.07,"mRainDropsCollisionRadius":2.5,"mRainDropsGravity":0.2,"mRainDropsPaintRadius":19.125,"mRainDropsPaintRadiusMax":19.125,"mRainDropsPaintRadiusRateHigh":1,"mRainDropsPaintRadiusRateMid":1,"mRainDropsTotalNum":192,"mRainWaitFrame":15,"mRiseFrame":45,"mRiseHeight":200,"mRiseRotateMaxDegArriveFrame":9,"mRiseRotateMaxDegPerFrame":-30,"mShape_SphereD":5,"mShape_SphereR":2}},"AquaBall":{"Id":11,"Name":"AquaBall","param":{"mBreak_NoDamageFrm":30,"mBurst_Damage_Far":550,"mBurst_Damage_HalfSphereThresholdY":45,"mBurst_Damage_Middle":550,"mBurst_Damage_Near":1800,"mBurst_KnockBackCoreImpact":6,"mBurst_KnockBackKb":0.2,"mBurst_KnockBackRadius":140,"mBurst_PaintR":70,"mBurst_Radius_Far":120,"mBurst_Radius_FarHigh":140,"mBurst_Radius_FarMid":130,"mBurst_Radius_Middle":120,"mBurst_Radius_MiddleHigh":140,"mBurst_Radius_MiddleMid":130,"mBurst_Radius_Near":80,"mBurst_Radius_NearHigh":80,"mBurst_Radius_NearMid":80,"mBurst_SplashAroundFuzzyRate":2,"mBurst_SplashNum":15,"mBurst_SplashOfstY":5,"mBurst_SplashPaintR":7.5,"mBurst_SplashPitH":30,"mBurst_SplashPitL":5,"mBurst_SplashVelH":6,"mBurst_SplashVelL":5,"mBurst_WarnFrm":40,"mCharge_Frm":46,"mColBullet_ColR":10,"mColGnd_ColR":10,"mColPlayer_ColR":10,"mCrossPaintRadius":25,"mCrossPaintRayLength":25,"mCrossPaintRayRadius":1,"mDiveFloatVelB":0.5,"mDiveFloatVelH":2.8,"mDiveFloatVelL":0.6,"mGripB":0.7,"mGripL":0.55,"mHP_High":6000,"mHP_Low":4000,"mHP_Mid":5000,"mHitDamage":500,"mHitWallSafePointCenterOffsetY":7.5,"mJump_KeepFrm":180,"mJump_LandFreeze_AllowRt":0.1,"mKnockBackCoreImpact":1,"mKnockBackKb":0,"mKnockBackRadius":300,"mLandingPaintRadius":35,"mMove_AccGnd":0.08,"mMove_AccGnd_Air":0.06,"mMove_AirKd_XZ":0.96,"mMove_BrkGnd":0.04,"mMove_BrkGnd_C":0.02,"mMove_BrkGnd_W":0.02,"mMove_TrnGnd":0.8,"mMove_VelGnd":1.44,"mMove_VelGnd_Enemy":0.24,"mMove_VelGnd_Stealth":1.68,"mNoCharge_Frm":70,"mObjectEffect_Up_DamageRt_High":1.3,"mObjectEffect_Up_DamageRt_Low":1,"mObjectEffect_Up_DamageRt_Mid":1.15,"mOcta_AlwaysSpecial_NoChargeFrm_SettingOcta_":0,"mPaintCheckHeight":20,"mPaintCheckPosOffsetSpeedRate":3,"mPaintCheckPosOffsetSpeedRateWallY_D":14,"mPaintCheckPosOffsetSpeedWallY_D":-15,"mPaintGauge_PointFull":180,"mPaintGauge_SpecialFrm":360,"mPaintRadius":10,"mUnrelaxFrm":25,"mWallCheckOffsetY":4.5,"mWallDrop_Detach_Impact":1,"mWallDrop_Detach_PeakDirAngleDeg":30,"mWallDrop_Detach_Reject":1}},"SuperBubble":{"Id":12,"Name":"SuperBubble","param":{"mAirResistXZ":0.004,"mAirResistY":0.01,"mBombCoreRadiusRateHigh":1.3,"mBombCoreRadiusRateMid":1.18,"mBoundPaintDamageRateMax":0.4,"mBoundPaintDamageRateMin":0.1,"mBoundPaintRadiusMax":32.4,"mBoundPaintRadiusMin":16.2,"mBoundPaintRadiusWallRate":1,"mBurst_CheckPaintUnderLength":100,"mBurst_Damage_Far":500,"mBurst_Damage_Middle":500,"mBurst_Damage_Near":2500,"mBurst_PaintR":56,"mBurst_PaintRFirstShotRate":0.85,"mBurst_PaintRHigh":80,"mBurst_PaintRMid":68,"mBurst_PaintRSecondShotRate":0.9,"mBurst_PaintRThirdShotRate":1,"mBurst_Radius_Far":120,"mBurst_Radius_FirstShotRate":0.85,"mBurst_Radius_Middle":120,"mBurst_Radius_Near":55,"mBurst_Radius_SecondShotRate":0.9,"mBurst_Radius_ThirdShotRate":1,"mBurst_WaitFrame":30,"mCameraNotObstructTimes":3,"mCameraObstructFrame":15,"mCameraObstructMinAlpha":1,"mCollisionFieldPlayerRadiusBottom":false,"mCollisionFieldRadius":8,"mCollisionPlayerRadiusBias":0.5,"mCollisionPlayerRadiusMax":20,"mCollisionPlayerRadiusMaxDamageRate":0.4,"mCollisionPlayerRadiusMaxFirstShotRate":0.85,"mCollisionPlayerRadiusMaxHigh":35,"mCollisionPlayerRadiusMaxMid":27.5,"mCollisionPlayerRadiusMaxSecondShotRate":0.9,"mCollisionPlayerRadiusMaxThirdShotRate":1,"mCollisionPlayerRadiusMin":8,"mCollisionRadiusForPlayerSwellFrame":30,"mCrossPaintRadius":45,"mCrossPaintRayLength":45,"mCrossPaintRayRadius":1,"mDamagePerFrame":5,"mDamageSwellStopFrame":60,"mFriendTeamDamageRate":1.2,"mGravity":0.005,"mGravity0AirResist0Frame":5,"mGroundCrossBoundRate":0.92,"mGroundNrmBoundAddSpeed":0.25,"mGroundNrmBoundRate":0.92,"mHPAddPerFrame":5,"mHPBurst":8000,"mHPDefault":4000,"mHPTimeOutReducePerFrame":600,"mInitVel":[0,0.5,1.2],"mInterpolationBoundRate":true,"mLifeFrame":840,"mLifeFrameExpandHit":120,"mLifeFrameMax":1800,"mMotionCancelFrm":30,"mMoveSpeed":0.6,"mObjectDamageRateHigh":1.3,"mObjectDamageRateMid":1.3,"mPaintGauge_PointFull":180,"mPaintGauge_SpecialFrm":480,"mRepeatFrame":45,"mSplashAirResist":0.1,"mSplashColRadius":3,"mSplashDrawRadius":3,"mSplashGravity":0.5,"mSplashPaintRadius":8,"mSplashSpanFrame":30,"mSwellingEnemyTeamDamageRate":0.8,"mSwingLiftFrame":1,"mSwingShotTiming":12,"mWallCrossBoundRate":0.65,"mWallNrmBoundAddSpeed":0,"mWallNrmBoundRate":0.65}},"SuperBall":{"Id":17,"Name":"SuperBall","param":{"mActivateBulletWaitFrm":30,"mArmor_ColOffsetY":10,"mArmor_ColRadius":10,"mArmor_DamageEffect_Num":0,"mArmor_HP":4700,"mArmor_MyColor_Bias":0.5,"mArmor_MyColor_InBias":0.35,"mArmor_MyColor_Min":1,"mArmor_ReleaseTimingFrm":65,"mArmor_WearTimingFrm":30,"mBiasBurstMax":0.6,"mBringCloseRateCrossVec":0.7,"mBringCloseRateMoveVec":0.7,"mBurst_Damage_Near":33,"mBurst_KnockBackCoreImpact":0.4,"mBurst_KnockBackKb":0.8,"mBurst_KnockBackRadius":80,"mBurst_PaintR":25,"mBurst_Radius_Near":10,"mChargeRtAutoIncr_High":0.01,"mChargeRtAutoIncr_Low":0.002,"mChargeRtAutoIncr_Mid":0.006,"mChargeRtPerNiceFriend1":0.08,"mChargeRtPerNiceFriend2":0.04,"mChargeRtPerNiceFriend3":0.02,"mChargeRtPerNiceFriend4":0.01,"mChargeRtPerNiceFriend5":0.01,"mChargeRtPerNiceMine":0.07,"mCol_Height":18,"mCol_TransformFrm":15,"mConveyer_Radius":5,"mCrossPaintRadius":15,"mCrossPaintRayLength":15,"mCrossPaintRayRadius":1,"mDamageDirect":0,"mDegRotatePaintTex":8.5,"mEffectShakeRange":70,"mFly_Gravity":0.21,"mFly_InitPit":0,"mFly_InitRol":0,"mFly_RadiusColPlayer":5,"mFly_RotI":20,"mFly_RotKd":1,"mFly_StraightFrame":17,"mFly_VelKd":0.955,"mFootSplashColRadius":2.5,"mFootSplashDrawRadius":3,"mFootSplashInitSpeed":0.75,"mFootSplashPaintRadius":40,"mFrameBurstToMax":90,"mFramePreBurst":30,"mGuideCheckCollisionFrame":216,"mGuideCheckCollisionSpan":6,"mGuideCheckEndFrame":216,"mHover_AdditionalFrm":5,"mHover_Altitude":40,"mHover_WaitFrm":16,"mIntervalPaint":6,"mKnockBackDirect":0.2,"mNiceAccept_AcceptFrm":5,"mNiceAccept_HandleFrm":10,"mNice_TravelDistanceH":600,"mNice_TravelFrameH":30,"mNice_TravelFrameL":10,"mNoRejectImpact_Frm":180,"mObjectEffect_Up_DamageRt_High":1.1,"mObjectEffect_Up_DamageRt_Low":1,"mObjectEffect_Up_DamageRt_Mid":1.05,"mPaintGauge_SpecialFrm":600,"mRadiusBurstMax":120,"mRadiusChargeMax":3,"mRadiusChargeMin":3,"mRadiusPaintMax":140,"mRadiusSoundShape_BeforeBurst":30,"mRejectResolve_Kf":0.1,"mRejectResolve_Kf_AfterFinish":0.4,"mShape_SphereR":2,"mShotVelZ":10,"mThanks_PaintPoint1":6,"mThanks_PaintPoint2":3,"mThanks_PaintPoint3":2,"mThanks_PaintPoint4":1,"mThanks_PaintPoint5":0.5,"mThanks_PaintPointMax":15,"mThanks_TravelDistanceH":600,"mThanks_TravelFrameH":30,"mThanks_TravelFrameL":10,"mTurnKf_ShotJump":0.5,"mVelGnd_ChargeFull":0,"mVelGnd_Charging":0}},"SuperStamp":{"Id":18,"Name":"SuperStamp","param":{"mAirResistXZ":0.97,"mAirResistY":0.97,"mBangDownBig_Backswing_AnimFrame":29,"mBangDownBig_Backswing_Frame":23,"mBangDownBig_BangDown_Frame":14,"mBangDownBig_BulletCollisionEnFrame":32,"mBangDownBig_BulletCollisionStFrame":26,"mBangDownBig_MoveImpact_Frame":20,"mBangDownBig_MoveImpact_Magnitude":1.6,"mBangDownBig_PaintAndBlast_Frame":28,"mBangDownBig_ShaftCollisionStFrame":23,"mBangDownSmall_Backswing_AnimFrame":31,"mBangDownSmall_Backswing_AnimStFrame_FromGird":10,"mBangDownSmall_Backswing_AnimStFrame_FromRA2BDS":30,"mBangDownSmall_Backswing_BlendFrame_FromGird":10,"mBangDownSmall_Backswing_Frame":8,"mBangDownSmall_BangDown_Frame":5,"mBangDownSmall_BulletCollisionEnFrame":13,"mBangDownSmall_BulletCollisionStFrame":9,"mBangDownSmall_BulletShieldThickNess":0,"mBangDownSmall_BulletShieldWidth":31.8,"mBangDownSmall_JumpGnd":1,"mBangDownSmall_MoveImpact_Frame":10,"mBangDownSmall_MoveImpact_Magnitude":2.2,"mBangDownSmall_PaintAndBlast_Frame":11,"mBangDownSmall_TurnLimitAngleDeg":5.2,"mDebugViewBulletCollision":false,"mEmptySign_RemainingFrame":120,"mFly_StraightFrame":8,"mGird_Frame":10,"mGird_NoSquidFrame":4,"mGird_TurnLimitAngleDeg":4,"mGird_VelGndBias":0.4,"mGird_VelGndEn":0.4,"mGird_VelGndSt":0,"mGravity":0.13,"mHoldCollsionValid":1,"mHoldPlayerBulletCollisionOffset0":[0,0,8.5],"mHoldPlayerBulletCollisionOffset1":[0,-0.3,-4.5],"mHoldPlayerBulletCollisionSize0":[31.8,31.8,10],"mHoldPlayerBulletCollisionSize1":[18,18.3,16],"mPaintGauge_SpecialFrm":540,"mPaintGauge_SpecialFrmH":660,"mPaintGauge_SpecialFrmM":600,"mRA2BDS_Frame":6,"mRollingAttack_NoSquidFrame":10,"mRollingAttack_ReadyFrame":6,"mRollingAttack_RollingFrame":30,"mRollingAttack_SafeAltitude":10,"mRotI":1,"mRotResist":1,"mSwingBigBurst_Damage_Far":400,"mSwingBigBurst_Damage_Middle":400,"mSwingBigBurst_Damage_Near":400,"mSwingBigBurst_KnockBackCoreImpact":2,"mSwingBigBurst_KnockBackKb":0.8,"mSwingBigBurst_KnockBackRadius":80,"mSwingBigBurst_Radius_Far":28,"mSwingBigBurst_Radius_Middle":20,"mSwingBigBurst_Radius_Near":20,"mSwingBigPaint_Radius":13,"mSwingBigPaint_SpanFrame":1,"mSwingBigPaint_StartFrame":0,"mSwingDamage":1000,"mSwingFieldCollisionOffset":[0,0,0],"mSwingFieldCollisionRadius":13.5,"mSwingJumpPaint_GroundRadius":16,"mSwingJumpPaint_SpanFrame":1,"mSwingJumpPaint_StartFrame":0,"mSwingJumpPaint_WallRadius":13,"mSwingJumpPanelNoPaintDiffHeight":3,"mSwingJumpPlayerBulletCollisionOffset0":[0,0,8.5],"mSwingJumpPlayerBulletCollisionOffset1":[0,-0.3,-4.5],"mSwingJumpPlayerBulletCollisionSize0":[31.8,31.8,10],"mSwingJumpPlayerBulletCollisionSize1":[18,18.3,16],"mSwingJumpPlayerCollisionUseHoldCollision":true,"mSwingPlayerBulletCollisionOffset0":[0,0,8.5],"mSwingPlayerBulletCollisionOffset1":[0,-0.3,-4.5],"mSwingPlayerBulletCollisionOffset2SolidPosZ":[0,0,8.5],"mSwingPlayerBulletCollisionSize0":[31.8,31.8,10],"mSwingPlayerBulletCollisionSize1":[18,18.3,16],"mSwingPlayerBulletCollisionSize2Max":[47.7,31.8,26],"mSwingPlayerBulletCollisionSize2MaxAngleX":30,"mSwingPlayerBulletCollisionSize2Min":[31.8,31.8,10],"mSwingPlayerBulletCollisionSize2MinAngleX":70,"mSwingPlayerCollisionUseHoldCollision":true,"mSwingSmallBurst_Damage_Far":400,"mSwingSmallBurst_Damage_Middle":400,"mSwingSmallBurst_Damage_Near":400,"mSwingSmallBurst_KnockBackCoreImpact":2,"mSwingSmallBurst_KnockBackKb":0.8,"mSwingSmallBurst_KnockBackRadius":60,"mSwingSmallBurst_Radius_Far":28,"mSwingSmallBurst_Radius_Middle":20,"mSwingSmallBurst_Radius_Near":20,"mSwingSmallPaint_Radius":13,"mSwingSmallPaint_SpanFrame":1,"mSwingSmallPaint_StartFrame":0,"mSwingStampPaintSize":[50,50],"mSwingUpDamageOn":false,"mSwing_KnockBackCoreImpact":2,"mSwing_KnockBackKb":0.8,"mSwing_KnockBackRadius":80,"mThrowBulletCollisionRadius":13,"mThrowBurst_Damage_Far":300,"mThrowBurst_Damage_Middle":300,"mThrowBurst_Damage_Near":600,"mThrowBurst_KnockBackCoreImpact":2,"mThrowBurst_KnockBackKb":0.8,"mThrowBurst_KnockBackRadius":80,"mThrowBurst_Radius_Far":80,"mThrowBurst_Radius_Middle":80,"mThrowBurst_Radius_Near":40,"mThrowDamage":1200,"mThrowFieldCollisionOffset":[0,0,0],"mThrowFieldCollisionRadius":11,"mThrowPlayerCollisionCenterOffset":[0,0,0],"mThrowPlayerCollisionCenterRadius":13,"mThrowPlayerCollisionCutAddLengthPerFrame":1,"mThrowPlayerCollisionCutWaitFrame":10,"mThrowPlayerCollisionSub1OffsetYPlusMinus":17,"mThrowPlayerCollisionSub1Radius":9,"mThrowPlayerCollisionSub2OffsetYPlusMinus":27.5,"mThrowPlayerCollisionSub2Radius":8,"mThrowStampPaintRadius":50,"mThrow_BackswingFrame":40,"mThrow_CrossPaintRadius":25,"mThrow_CrossPaintRayLength":25,"mThrow_CrossPaintRayRadius":1,"mThrow_KnockBackCoreImpact":2,"mThrow_KnockBackDegree":45,"mThrow_KnockBackKb":0.8,"mThrow_KnockBackRadius":80,"mTurnKf_ShotJump":0.5,"mVelLimit_NoPaint":1.44,"mVelLimit_OpInk":0.24,"mWeaponAnim_Return_PlFrm_AtBangDownSmall":10,"mWeaponAnim_Return_PlFrm_AtGird":30,"mWeaponAnim_Return_StFrm_AtBangDownSmall":1,"mWeaponAnim_Return_StFrm_AtGird":4,"mWeaponAnim_Smash_PlFrm_AtBangDownBig":14,"mWeaponAnim_Smash_PlFrm_AtBangDownSmall":3,"mWeaponAnim_Smash_StFrm_AtBangDownBig":28,"mWeaponAnim_Smash_StFrm_AtBangDownSmall":10}}}}